logicds6/__init__.py
logicds6/logicds66.py
logicds6/main.py
logicds6/setup.py
logicds6-0.0.1.dist-info/LICENSE
logicds6-0.0.1.dist-info/METADATA
logicds6-0.0.1.dist-info/WHEEL
logicds6-0.0.1.dist-info/top_level.txt
logicds6-0.0.1.dist-info/RECORD
