Metadata-Version: 2.1
Name: logicds6
Version: 0.0.1
Summary: LogicDS reasoning-based universal language teaching library
Home-page: https://github.com/brn378/logicds
Author: Barnas Monteith,LogicDS
Author-email: barnas@engagescience.org
Classifier: Programming Language :: Python :: 3
Classifier: License :: OSI Approved :: MIT License
Classifier: Operating System :: OS Independent
License-File: LICENSE
